<?xml version = '1.0' encoding = 'UTF-8'?>
<Relation class="oracle.dbtools.crest.model.design.logical.Relation" name="Relation_3" directorySegmentName="seg_0" id="996A57B6-2203-5501-3172-CCF8ABBD472A">
<createdBy>yumin</createdBy>
<createdTime>2026-05-15 23:02:37 UTC</createdTime>
<ownerDesignName>modelo_Challenge</ownerDesignName>
<engineerTo>
<item key="AB6CB75E-7BBB-95AA-F9E8-B5F4C7E93268" value="true"/>
</engineerTo>
<sourcePk>C6E342B9-6397-E2F6-708D-C739988E5626</sourcePk>
<identifying>false</identifying>
<optionalSource>true</optionalSource>
<optionalTarget>false</optionalTarget>
<sourceCardinality>1</sourceCardinality>
<sourceEntity>6C389B84-623E-4BCE-3638-2BFE6497060E</sourceEntity>
<targetCardinalityString>*</targetCardinalityString>
<targetEntity>F8931770-82F4-1127-121E-2271C96521DE</targetEntity>
<transferable>true</transferable>
<deleteRule>NO ACTION</deleteRule>
</Relation>